[
    {
        "id":"1",
        "name":"",
        "description":"He hecho más de 20 carteles para eventos de música electrónica",
        "tools":"",
        "img":"",
        "status":""
    },
    {
        "id":"2",
        "name":"",
        "description":"He crecido entre abejas, mi familia es apicultora",
        "tools":"",
        "img":"",
        "status":""
    },
    {
        "id":"3",
        "name":"",
        "description":"Mi perro se llama Rasputín",
        "tools":"",
        "img":"",
        "status":""
    },
    {
        "id":"4",
        "name":"",
        "description":"He vivido en Bristol, UK",
        "tools":"",
        "img":"",
        "status":""
    },
    {
        "id":"5",
        "name":"",
        "description":"Tengo más de 50 plantas en casa",
        "tools":"",
        "img":"",
        "status":""
    },
    {
        "id":"6",
        "name":"",
        "description":"Tenía un colección de películas Disney, y me sabía los diálogos de todas",
        "tools":"",
        "img":"",
        "status":""
    },
    {
        "id":"7",
        "name":"",
        "description":"Soy la nieta de Isabel la de bolo y de Rafel de Bruno",
        "tools":"",
        "img":"",
        "status":""
    },
    {
        "id":"8",
        "name":"",
        "description":"",
        "tools":"",
        "img":"",
        "status":""
    },
    {
        "id":"9",
        "name":"",
        "description":"",
        "tools":"",
        "img":"",
        "status":""
    },
    {
        "id":"10",
        "name":"",
        "description":"",
        "tools":"",
        "img":"",
        "status":""
    },
    {
        "id":"11",
        "name":"",
        "description":"",
        "tools":"",
        "img":"",
        "status":""
    },
    {
        "id":"12",
        "name":"",
        "description":"",
        "tools":"",
        "img":"",
        "status":""
    },
    {
        "id":"13",
        "name":"",
        "description":"",
        "tools":"",
        "img":"",
        "status":""
    },
    {
        "id":"14",
        "name":"",
        "description":"",
        "tools":"",
        "img":"",
        "status":""
    },
    {
        "id":"15",
        "name":"",
        "description":"",
        "tools":"",
        "img":"",
        "status":""
    },
    {
        "id":"16",
        "name":"",
        "description":"",
        "tools":"",
        "img":"",
        "status":""
    },
    {
        "id":"17",
        "name":"",
        "description":"",
        "tools":"",
        "img":"",
        "status":""
    },
    {
        "id":"18",
        "name":"",
        "description":"",
        "tools":"",
        "img":"",
        "status":""
    },
    {
        "id":"19",
        "name":"",
        "description":"",
        "tools":"",
        "img":"",
        "status":""
    },
    {
        "id":"20",
        "name":"",
        "description":"",
        "tools":"",
        "img":"",
        "status":""
    }
]